Semis/8-bitShiftRegister.v
`timescale 1ns / 1ps

module eight_bb (
    input wire clk,
    input wire rst,
    input wire shift_left,  // Shift direction control
    input wire shift_right, // Shift direction control
    input wire serial_in,   // Serial input bit
    output reg [7:0] q      // 8-bit output register
);

always @(posedge clk or posedge rst) begin
    if (rst) begin
        q <= 8'b00000000;  // Reset to 0
    end else begin
        if (shift_left) begin
            q <= {q[6:0], serial_in}; // Shift left and input new bit on LSB
        end else if (shift_right) begin
            q <= {serial_in, q[7:1]}; // Shift right and input new bit on MSB
        end
    end
end

endmodule

//========================//
// Testbench for eight_bb      //
//========================//
module tb_eight_bb;

    reg clk;
    reg rst;
    reg shift_left;
    reg shift_right;
    reg serial_in;
    wire [7:0] q;

    // Instantiate the 8-bit shift register (8_bb)
    eight_bb uut (
        .clk(clk),
        .rst(rst),
        .shift_left(shift_left),
        .shift_right(shift_right),
        .serial_in(serial_in),
        .q(q)
    );

    // Clock generation (10ns period)
    always #5 clk = ~clk;

    initial begin
        // Optional: dump waveform if using GTKWave
        $dumpfile("8-bitShiftRegister.vcd");
        $dumpvars(0, tb_eight_bb);

        // Monitor changes
        $monitor("Time=%0t | rst=%b shift_left=%b shift_right=%b serial_in=%b => q=%b", 
                 $time, rst, shift_left, shift_right, serial_in, q);

        // Initialize inputs
        clk = 0;
        rst = 1;
        shift_left = 0;
        shift_right = 0;
        serial_in = 0;

        #10 rst = 0; // Clear reset

        // Test sequence
        #10 shift_left = 1; serial_in = 1;  // Shift left → q=00000001
        #10 shift_left = 1; serial_in = 0;  // Shift left → q=00000010
        #10 shift_left = 1; serial_in = 1;  // Shift left → q=00000101
        #10 shift_right = 1; serial_in = 0; // Shift right → q=10000101
        #10 shift_right = 1; serial_in = 1; // Shift right → q=11000101
        #10 shift_left = 1; serial_in = 0;  // Shift left → q=10000100
        #10 shift_left = 1; serial_in = 1;  // Shift left → q=00001001
        #10 shift_right = 1; serial_in = 1; // Shift right → q=10001001
        #10 shift_left = 0; shift_right = 0; // Hold

        #20 $finish;  // End simulation
    end

endmodule

Semis/8-bitShiftRegister.vcd
$date
	Wed May 28 02:02:19 2025
$end
$version
	Icarus Verilog
$end
$timescale
	1ps
$end
$scope module tb_eight_bb $end
$var wire 8 ! q [7:0] $end
$var reg 1 " clk $end
$var reg 1 # rst $end
$var reg 1 $ serial_in $end
$var reg 1 % shift_left $end
$var reg 1 & shift_right $end
$scope module uut $end
$var wire 1 " clk $end
$var wire 1 # rst $end
$var wire 1 $ serial_in $end
$var wire 1 % shift_left $end
$var wire 1 & shift_right $end
$var reg 8 ' q [7:0] $end
$upscope $end
$upscope $end
$enddefinitions $end
#0
$dumpvars
b0 '
0&
0%
0$
1#
0"
b0 !
$end
#5000
1"
#10000
0"
0#
#15000
1"
#20000
0"
1$
1%
#25000
b1 !
b1 '
1"
#30000
0"
0$
#35000
b10 !
b10 '
1"
#40000
0"
1$
#45000
b101 !
b101 '
1"
#50000
0"
0$
1&
#55000
b1010 !
b1010 '
1"
#60000
0"
1$
#65000
b10101 !
b10101 '
1"
#70000
0"
0$
#75000
b101010 !
b101010 '
1"
#80000
0"
1$
#85000
b1010101 !
b1010101 '
1"
#90000
0"
#95000
b10101011 !
b10101011 '
1"
#100000
0"
0&
0%
